README.md
setup.py
keytar/__init__.py
keytar/cloud_data_store.py
keytar/database.py
keytar/db_types.py
keytar/dynamo.py
keytar/key.py
keytar/mongo.py
keytar/query.py
keytar/redis.py
keytar/where.py
keytar.egg-info/PKG-INFO
keytar.egg-info/SOURCES.txt
keytar.egg-info/dependency_links.txt
keytar.egg-info/requires.txt
keytar.egg-info/top_level.txt