Metadata-Version: 1.1
Name: keytar
Version: 0.1.0
Summary: Key Value Db Wrapper
Home-page: https://github.com/mattmatters/keytar
Author: Matt Lewis
Author-email: domattthings@gmail.com
License: MIT
Download-URL: https://github.com/mattmatters/keytar/archive/0.1.0.tar.gz
Platform: UNKNOWN
